amgxp/__init__.py
amgxp-1.0.dist-info/METADATA
amgxp-1.0.dist-info/WHEEL
amgxp-1.0.dist-info/top_level.txt
amgxp-1.0.dist-info/RECORD
