Metadata-Version: 2.1
Name: amgxp
Version: 1.0
Summary: Simple Package for Beauty Coding
Author: vardxg
Author-email: <vardxgx@gmail.com>
Keywords: python
Classifier: Development Status :: 1 - Planning
Classifier: Intended Audience :: Developers
Classifier: Programming Language :: Python :: 3
Classifier: Operating System :: Unix
Classifier: Operating System :: MacOS :: MacOS X
Classifier: Operating System :: Microsoft :: Windows
Requires-Dist: vardxg
